cmlibs/__init__.py
cmlibs/widgets/__init__.py
cmlibs/widgets/addviewwidget.py
cmlibs/widgets/alignmentsceneviewerwidget.py
cmlibs/widgets/base.py
cmlibs/widgets/basesceneviewerwidget.py
cmlibs/widgets/collapsibleboxwidget.py
cmlibs/widgets/consoleeditorwidget.py
cmlibs/widgets/definitions.py
cmlibs/widgets/draggablelistwidget.py
cmlibs/widgets/editabletabbar.py
cmlibs/widgets/enumerationchooserwidget.py
cmlibs/widgets/errors.py
cmlibs/widgets/exportwebgldialog.py
cmlibs/widgets/fieldchooserwidget.py
cmlibs/widgets/fieldconditions.py
cmlibs/widgets/fieldeditorwidget.py
cmlibs/widgets/fieldlisteditorwidget.py
cmlibs/widgets/fieldpropertieswidget.py
cmlibs/widgets/fieldtypechooserwidget.py
cmlibs/widgets/glyphchooserwidget.py
cmlibs/widgets/graphicseditorwidget.py
cmlibs/widgets/groupeditorwidget.py
cmlibs/widgets/interactiveconsolewidget.py
cmlibs/widgets/logspinbox.py
cmlibs/widgets/logviewerwidget.py
cmlibs/widgets/materialchooserwidget.py
cmlibs/widgets/materialeditorwidget.py
cmlibs/widgets/mesheditorwidget.py
cmlibs/widgets/modelsourceseditorwidget.py
cmlibs/widgets/regionchooserwidget.py
cmlibs/widgets/regioneditorwidget.py
cmlibs/widgets/sceneeditorwidget.py
cmlibs/widgets/scenelayoutchooserdialog.py
cmlibs/widgets/sceneviewereditorwidget.py
cmlibs/widgets/sceneviewerwidget.py
cmlibs/widgets/snapshotdialog.py
cmlibs/widgets/spectrumchooserwidget.py
cmlibs/widgets/spectrumeditorwidget.py
cmlibs/widgets/tessellationchooserwidget.py
cmlibs/widgets/tessellationeditorwidget.py
cmlibs/widgets/timeeditorwidget.py
cmlibs/widgets/utils.py
cmlibs/widgets/viewwidget.py
cmlibs/widgets/viewwidgetdescription.py
cmlibs/widgets/delegates/__init__.py
cmlibs/widgets/delegates/checkboxdelegate.py
cmlibs/widgets/delegates/spinboxdelegate.py
cmlibs/widgets/fields/__init__.py
cmlibs/widgets/fields/lists.py
cmlibs/widgets/fields/parsers.py
cmlibs/widgets/fields/requirements.py
cmlibs/widgets/handlers/__init__.py
cmlibs/widgets/handlers/abstracthandler.py
cmlibs_widgets-0.9.3.dist-info/licenses/LICENSE
cmlibs_widgets-0.9.3.dist-info/METADATA
cmlibs_widgets-0.9.3.dist-info/WHEEL
cmlibs_widgets-0.9.3.dist-info/top_level.txt
cmlibs_widgets-0.9.3.dist-info/RECORD
