Metadata-Version: 2.4
Name: cmlibs.widgets
Version: 0.9.3
Summary: A collection of Qt widgets and utilities for handling user interface interactions with the CMLibs Zinc library.
Author-email: Hugh Sorby <h.sorby@auckland.ac.nz>
License: Mozilla Public License, version 2.0
Project-URL: Homepage, https://cmlibs.org
Project-URL: Repository, https://github.com/CMLibs-Python/cmlibs.widgets
Keywords: CMLibs,Zinc,Widgets,UI
Classifier: Programming Language :: Python :: 3
Classifier: Operating System :: OS Independent
Classifier: Topic :: Scientific/Engineering :: Medical Science Apps.
Requires-Python: >=3.8
License-File: LICENSE
Requires-Dist: cmlibs.maths>=0.3
Requires-Dist: cmlibs.utils>=0.6
Requires-Dist: PySide6
Requires-Dist: cmlibs.zinc>=4.0
Requires-Dist: cmlibs.argon>=0.4.0
Dynamic: license-file
